{
    "info": {
        "device": "cuda",
        "epoch": 20,
        "dataset": "stl10",
        "data_path": "/host/ubuntu/torch",
        "bs": 32,
        "root_path": "/host/ubuntu/torch",
        "arch": "resnext50_32x4d",
        "lr": 0.001,
        "lr_scheduler": "step",
        "lr_step": 5,
        "lr_gamma": 0.5,
        "lr_scale": 0.1,
        "limit_train": 0,
        "limit_test": 0,
        "stats_fp": "./logs/massA/stats_210716_034228.json",
        "lineareval": true,
        "earlystop_epoch": 5,
        "pretrained": true,
        "note": "",
        "opt": "adamw",
        "fc": [
            512,
            128,
            32
        ],
        "image_size": 224
    },
    "telem": {
        "hardware": "1x3090",
        "sample_count_train": 5000,
        "sample_count_val": 8000,
        "completed": false,
        "time_stamp": "210716_034228",
        "time_start": 1626406967.6458905,
        "time_finish": 1626407616.064594,
        "time_elapsed": 648.4187035560608,
        "time_updated": 1626407616.0646,
        "bs": null,
        "mode": "lineareval"
    },
    "results": {
        "epochs": 19,
        "epoch.time": 32.21510103940964,
        "epoch.sample_time": 0.0,
        "train.time": 12.54069209098816,
        "val.time": 19.67440894842148,
        "train.sample_time": 0.002508138418197632,
        "val.sample_time": 0.002459301118552685,
        "train.acc": 0.9864,
        "train.loss": 9.999,
        "val.acc": 0.9625,
        "val.loss": 9.999
    },
    "train": [
        {
            "epoch": 0,
            "sample": 5000,
            "lr": 0.0010000000000000002,
            "loss": 0.4549311184484488,
            "acc": 0.8572,
            "time": 12.525280714035034,
            "time_start": 1626406967.6458905,
            "time_finish": 1626406980.1711712,
            "time_cost": 12.525280714035034
        },
        {
            "epoch": 1,
            "sample": 5000,
            "lr": 0.0010000000000000002,
            "loss": 0.2105557965529952,
            "acc": 0.9358,
            "time": 12.557552814483643,
            "time_start": 1626407000.178196,
            "time_finish": 1626407012.7357488,
            "time_cost": 12.557552814483643
        },
        {
            "epoch": 2,
            "sample": 5000,
            "lr": 0.0010000000000000002,
            "loss": 0.16368756285174543,
            "acc": 0.947,
            "time": 12.447881698608398,
            "time_start": 1626407032.5726442,
            "time_finish": 1626407045.020526,
            "time_cost": 12.447881698608398
        },
        {
            "epoch": 3,
            "sample": 5000,
            "lr": 0.0010000000000000002,
            "loss": 0.1557733002889925,
            "acc": 0.9484,
            "time": 12.467334270477295,
            "time_start": 1626407064.775629,
            "time_finish": 1626407077.2429633,
            "time_cost": 12.467334270477295
        },
        {
            "epoch": 4,
            "sample": 5000,
            "lr": 0.0010000000000000002,
            "loss": 0.13779301341967123,
            "acc": 0.951,
            "time": 12.527976989746094,
            "time_start": 1626407097.12378,
            "time_finish": 1626407109.651757,
            "time_cost": 12.527976989746094
        },
        {
            "epoch": 5,
            "sample": 5000,
            "lr": 0.0005000000000000001,
            "loss": 0.08344913035583724,
            "acc": 0.9724,
            "time": 12.4947988986969,
            "time_start": 1626407129.4752645,
            "time_finish": 1626407141.9700634,
            "time_cost": 12.4947988986969
        },
        {
            "epoch": 6,
            "sample": 5000,
            "lr": 0.0005000000000000001,
            "loss": 0.08214829763387194,
            "acc": 0.971,
            "time": 12.409472942352295,
            "time_start": 1626407161.6814048,
            "time_finish": 1626407174.0908778,
            "time_cost": 12.409472942352295
        },
        {
            "epoch": 7,
            "sample": 5000,
            "lr": 0.0005000000000000001,
            "loss": 0.08195988101822436,
            "acc": 0.971,
            "time": 12.563128232955933,
            "time_start": 1626407194.0239358,
            "time_finish": 1626407206.587064,
            "time_cost": 12.563128232955933
        },
        {
            "epoch": 8,
            "sample": 5000,
            "lr": 0.0005000000000000001,
            "loss": 0.0829158396053033,
            "acc": 0.9726,
            "time": 12.487309694290161,
            "time_start": 1626407226.3489232,
            "time_finish": 1626407238.836233,
            "time_cost": 12.487309694290161
        },
        {
            "epoch": 9,
            "sample": 5000,
            "lr": 0.0005000000000000001,
            "loss": 0.0715894798212833,
            "acc": 0.9746,
            "time": 12.569450616836548,
            "time_start": 1626407258.597225,
            "time_finish": 1626407271.1666756,
            "time_cost": 12.569450616836548
        },
        {
            "epoch": 10,
            "sample": 5000,
            "lr": 0.00025000000000000006,
            "loss": 0.05568800983204548,
            "acc": 0.9794,
            "time": 12.562678098678589,
            "time_start": 1626407291.0694249,
            "time_finish": 1626407303.632103,
            "time_cost": 12.562678098678589
        },
        {
            "epoch": 11,
            "sample": 5000,
            "lr": 0.00025000000000000006,
            "loss": 0.06558154476176248,
            "acc": 0.9786,
            "time": 12.50039553642273,
            "time_start": 1626407323.4108653,
            "time_finish": 1626407335.9112608,
            "time_cost": 12.50039553642273
        },
        {
            "epoch": 12,
            "sample": 5000,
            "lr": 0.00025000000000000006,
            "loss": 0.05517014649890921,
            "acc": 0.9796,
            "time": 12.685065507888794,
            "time_start": 1626407355.819637,
            "time_finish": 1626407368.5047026,
            "time_cost": 12.685065507888794
        },
        {
            "epoch": 13,
            "sample": 5000,
            "lr": 0.00025000000000000006,
            "loss": 0.058008021529345734,
            "acc": 0.9792,
            "time": 12.515612125396729,
            "time_start": 1626407388.5325203,
            "time_finish": 1626407401.0481324,
            "time_cost": 12.515612125396729
        },
        {
            "epoch": 14,
            "sample": 5000,
            "lr": 0.00025000000000000006,
            "loss": 0.05513605461485541,
            "acc": 0.982,
            "time": 12.548261165618896,
            "time_start": 1626407420.8650308,
            "time_finish": 1626407433.413292,
            "time_cost": 12.548261165618896
        },
        {
            "epoch": 15,
            "sample": 5000,
            "lr": 0.00012500000000000003,
            "loss": 0.049074825602746716,
            "acc": 0.9844,
            "time": 12.582523107528687,
            "time_start": 1626407453.3252933,
            "time_finish": 1626407465.9078164,
            "time_cost": 12.582523107528687
        },
        {
            "epoch": 16,
            "sample": 5000,
            "lr": 0.00012500000000000003,
            "loss": 0.04876381487683482,
            "acc": 0.9838,
            "time": 12.60512661933899,
            "time_start": 1626407485.906175,
            "time_finish": 1626407498.5113015,
            "time_cost": 12.60512661933899
        },
        {
            "epoch": 17,
            "sample": 5000,
            "lr": 0.00012500000000000003,
            "loss": 0.040024018893908164,
            "acc": 0.9864,
            "time": 12.60679292678833,
            "time_start": 1626407518.4693422,
            "time_finish": 1626407531.0761352,
            "time_cost": 12.60679292678833
        },
        {
            "epoch": 18,
            "sample": 5000,
            "lr": 0.00012500000000000003,
            "loss": 0.04648383333685861,
            "acc": 0.9824,
            "time": 12.555944442749023,
            "time_start": 1626407551.0332828,
            "time_finish": 1626407563.5892272,
            "time_cost": 12.555944442749023
        },
        {
            "epoch": 19,
            "sample": 5000,
            "lr": 0.00012500000000000003,
            "loss": 0.04154078608775841,
            "acc": 0.986,
            "time": 12.601255416870117,
            "time_start": 1626407583.5292127,
            "time_finish": 1626407596.1304681,
            "time_cost": 12.601255416870117
        }
    ],
    "val": [
        {
            "epoch": 0,
            "sample": 8000,
            "lr": 0.0,
            "loss": 0.20887221863120795,
            "acc": 0.9315,
            "time": 19.785847902297974,
            "time_start": 1626406980.273274,
            "time_finish": 1626407000.0591218,
            "time_cost": 19.785847902297974
        },
        {
            "epoch": 1,
            "sample": 8000,
            "lr": 0.0,
            "loss": 0.1567313738875091,
            "acc": 0.95075,
            "time": 19.618667364120483,
            "time_start": 1626407012.846346,
            "time_finish": 1626407032.4650133,
            "time_cost": 19.618667364120483
        },
        {
            "epoch": 2,
            "sample": 8000,
            "lr": 0.0,
            "loss": 0.20183026304654778,
            "acc": 0.93775,
            "time": 19.560382604599,
            "time_start": 1626407045.116124,
            "time_finish": 1626407064.6765065,
            "time_cost": 19.560382604599
        },
        {
            "epoch": 3,
            "sample": 8000,
            "lr": 0.0,
            "loss": 0.17360402150824666,
            "acc": 0.945125,
            "time": 19.684242486953735,
            "time_start": 1626407077.3506968,
            "time_finish": 1626407097.0349393,
            "time_cost": 19.684242486953735
        },
        {
            "epoch": 4,
            "sample": 8000,
            "lr": 0.0,
            "loss": 0.15986845317529513,
            "acc": 0.95275,
            "time": 19.612908124923706,
            "time_start": 1626407109.7555196,
            "time_finish": 1626407129.3684278,
            "time_cost": 19.612908124923706
        },
        {
            "epoch": 5,
            "sample": 8000,
            "lr": 0.0,
            "loss": 0.1479913592878729,
            "acc": 0.95625,
            "time": 19.50454044342041,
            "time_start": 1626407142.0776849,
            "time_finish": 1626407161.5822253,
            "time_cost": 19.50454044342041
        },
        {
            "epoch": 6,
            "sample": 8000,
            "lr": 0.0,
            "loss": 0.1440179537385702,
            "acc": 0.957125,
            "time": 19.716076374053955,
            "time_start": 1626407174.1982558,
            "time_finish": 1626407193.9143322,
            "time_cost": 19.716076374053955
        },
        {
            "epoch": 7,
            "sample": 8000,
            "lr": 0.0,
            "loss": 0.14136170685198157,
            "acc": 0.957875,
            "time": 19.57262873649597,
            "time_start": 1626407206.6770465,
            "time_finish": 1626407226.2496753,
            "time_cost": 19.57262873649597
        },
        {
            "epoch": 8,
            "sample": 8000,
            "lr": 0.0,
            "loss": 0.14890483969682827,
            "acc": 0.954375,
            "time": 19.56916642189026,
            "time_start": 1626407238.9349744,
            "time_finish": 1626407258.5041409,
            "time_cost": 19.56916642189026
        },
        {
            "epoch": 9,
            "sample": 8000,
            "lr": 0.0,
            "loss": 0.16357267759903335,
            "acc": 0.952875,
            "time": 19.690162181854248,
            "time_start": 1626407271.274697,
            "time_finish": 1626407290.9648592,
            "time_cost": 19.690162181854248
        },
        {
            "epoch": 10,
            "sample": 8000,
            "lr": 0.0,
            "loss": 0.146049060838297,
            "acc": 0.9565,
            "time": 19.578206062316895,
            "time_start": 1626407303.7245574,
            "time_finish": 1626407323.3027635,
            "time_cost": 19.578206062316895
        },
        {
            "epoch": 11,
            "sample": 8000,
            "lr": 0.0,
            "loss": 0.14596129395673052,
            "acc": 0.9565,
            "time": 19.689195156097412,
            "time_start": 1626407336.0200489,
            "time_finish": 1626407355.709244,
            "time_cost": 19.689195156097412
        },
        {
            "epoch": 12,
            "sample": 8000,
            "lr": 0.0,
            "loss": 0.13332171058957465,
            "acc": 0.958875,
            "time": 19.811187505722046,
            "time_start": 1626407368.6118422,
            "time_finish": 1626407388.4230297,
            "time_cost": 19.811187505722046
        },
        {
            "epoch": 13,
            "sample": 8000,
            "lr": 0.0,
            "loss": 0.138874272092944,
            "acc": 0.958,
            "time": 19.60009765625,
            "time_start": 1626407401.1552558,
            "time_finish": 1626407420.7553535,
            "time_cost": 19.60009765625
        },
        {
            "epoch": 14,
            "sample": 8000,
            "lr": 0.0,
            "loss": 0.1375026223328896,
            "acc": 0.960375,
            "time": 19.725868463516235,
            "time_start": 1626407433.5056064,
            "time_finish": 1626407453.2314749,
            "time_cost": 19.725868463516235
        },
        {
            "epoch": 15,
            "sample": 8000,
            "lr": 0.0,
            "loss": 0.14089816533541308,
            "acc": 0.959,
            "time": 19.784754514694214,
            "time_start": 1626407466.005069,
            "time_finish": 1626407485.7898235,
            "time_cost": 19.784754514694214
        },
        {
            "epoch": 16,
            "sample": 8000,
            "lr": 0.0,
            "loss": 0.1489071112407837,
            "acc": 0.959875,
            "time": 19.753391981124878,
            "time_start": 1626407498.6083288,
            "time_finish": 1626407518.3617208,
            "time_cost": 19.753391981124878
        },
        {
            "epoch": 17,
            "sample": 8000,
            "lr": 0.0,
            "loss": 0.1497830528380582,
            "acc": 0.96025,
            "time": 19.759495496749878,
            "time_start": 1626407531.1674523,
            "time_finish": 1626407550.9269478,
            "time_cost": 19.759495496749878
        },
        {
            "epoch": 18,
            "sample": 8000,
            "lr": 0.0,
            "loss": 0.1355296694317367,
            "acc": 0.9625,
            "time": 19.743129014968872,
            "time_start": 1626407563.692061,
            "time_finish": 1626407583.43519,
            "time_cost": 19.743129014968872
        },
        {
            "epoch": 19,
            "sample": 8000,
            "lr": 0.0,
            "loss": 0.13509888208867052,
            "acc": 0.9615,
            "time": 19.728230476379395,
            "time_start": 1626407596.242363,
            "time_finish": 1626407615.9705935,
            "time_cost": 19.728230476379395
        }
    ]
}