{
    "info": {
        "device": "cuda",
        "epoch": 10,
        "dataset": "cifar100",
        "bs": 2048,
        "data_path": "/host/ubuntu/torch",
        "arch": "dino_vits16",
        "lr": 0.001,
        "stats_json": "./logs/stats_latest.json"
    },
    "train": [
        {
            "epoch": 1,
            "time_start": 1624305253.8265076,
            "time_finish": 1624305260.2387772,
            "time_cost": 6.412269592285156,
            "loss": 4.48516622543335,
            "acc": 0.05558,
            "vram": 4.88232421875
        },
        {
            "epoch": 2,
            "time_start": 1624305261.9161162,
            "time_finish": 1624305268.429339,
            "time_cost": 6.513222694396973,
            "loss": 3.579096040725708,
            "acc": 0.22374,
            "vram": 4.88232421875
        },
        {
            "epoch": 3,
            "time_start": 1624305270.3171394,
            "time_finish": 1624305276.4183006,
            "time_cost": 6.101161241531372,
            "loss": 2.7739127349853514,
            "acc": 0.38234,
            "vram": 4.88232421875
        },
        {
            "epoch": 4,
            "time_start": 1624305278.1801546,
            "time_finish": 1624305284.0056884,
            "time_cost": 5.825533866882324,
            "loss": 2.282434482574463,
            "acc": 0.4877,
            "vram": 4.88232421875
        },
        {
            "epoch": 5,
            "time_start": 1624305285.7386284,
            "time_finish": 1624305291.7821548,
            "time_cost": 6.0435264110565186,
            "loss": 1.9362150764465331,
            "acc": 0.56612,
            "vram": 4.88232421875
        },
        {
            "epoch": 6,
            "time_start": 1624305293.506914,
            "time_finish": 1624305299.5732834,
            "time_cost": 6.066369533538818,
            "loss": 1.6326904249191285,
            "acc": 0.6374,
            "vram": 4.88232421875
        },
        {
            "epoch": 7,
            "time_start": 1624305301.2879145,
            "time_finish": 1624305307.357147,
            "time_cost": 6.06923246383667,
            "loss": 1.389968628883362,
            "acc": 0.7014200000000002,
            "vram": 4.88232421875
        },
        {
            "epoch": 8,
            "time_start": 1624305309.1862607,
            "time_finish": 1624305315.2032046,
            "time_cost": 6.01694393157959,
            "loss": 1.163842420578003,
            "acc": 0.76126,
            "vram": 4.88232421875
        },
        {
            "epoch": 9,
            "time_start": 1624305316.9948218,
            "time_finish": 1624305323.036129,
            "time_cost": 6.041307210922241,
            "loss": 0.9590958428382873,
            "acc": 0.81242,
            "vram": 4.88232421875
        },
        {
            "epoch": 10,
            "time_start": 1624305324.77768,
            "time_finish": 1624305331.0134223,
            "time_cost": 6.2357423305511475,
            "loss": 0.7997782063484192,
            "acc": 0.85128,
            "vram": 4.88232421875
        }
    ],
    "val": [
        {
            "epoch": 1,
            "time_start": 1624305260.243211,
            "time_finish": 1624305261.9096453,
            "time_cost": 1.6664342880249023,
            "loss": 4.101378917694092,
            "acc": 0.1324,
            "vram": 4.88232421875
        },
        {
            "epoch": 2,
            "time_start": 1624305268.4326851,
            "time_finish": 1624305270.307556,
            "time_cost": 1.874870777130127,
            "loss": 3.128486394882202,
            "acc": 0.3033,
            "vram": 4.88232421875
        },
        {
            "epoch": 3,
            "time_start": 1624305276.4228065,
            "time_finish": 1624305278.173605,
            "time_cost": 1.7507984638214111,
            "loss": 2.513276195526123,
            "acc": 0.43090000000000006,
            "vram": 4.88232421875
        },
        {
            "epoch": 4,
            "time_start": 1624305284.00897,
            "time_finish": 1624305285.73025,
            "time_cost": 1.7212798595428467,
            "loss": 2.111838388442993,
            "acc": 0.5221,
            "vram": 4.88232421875
        },
        {
            "epoch": 5,
            "time_start": 1624305291.78652,
            "time_finish": 1624305293.499119,
            "time_cost": 1.7125990390777588,
            "loss": 1.7819090604782104,
            "acc": 0.5994,
            "vram": 4.88232421875
        },
        {
            "epoch": 6,
            "time_start": 1624305299.5761633,
            "time_finish": 1624305301.2831955,
            "time_cost": 1.7070322036743164,
            "loss": 1.5297570943832397,
            "acc": 0.6616,
            "vram": 4.88232421875
        },
        {
            "epoch": 7,
            "time_start": 1624305307.361415,
            "time_finish": 1624305309.1720097,
            "time_cost": 1.8105947971343994,
            "loss": 1.2919095993041991,
            "acc": 0.7268000000000001,
            "vram": 4.88232421875
        },
        {
            "epoch": 8,
            "time_start": 1624305315.2075477,
            "time_finish": 1624305316.9850204,
            "time_cost": 1.777472734451294,
            "loss": 1.0782630681991576,
            "acc": 0.78,
            "vram": 4.88232421875
        },
        {
            "epoch": 9,
            "time_start": 1624305323.040676,
            "time_finish": 1624305324.768771,
            "time_cost": 1.7280948162078857,
            "loss": 0.864984667301178,
            "acc": 0.8354,
            "vram": 4.88232421875
        },
        {
            "epoch": 10,
            "time_start": 1624305331.0174143,
            "time_finish": 1624305332.8764484,
            "time_cost": 1.8590340614318848,
            "loss": 0.7426053643226623,
            "acc": 0.8648,
            "vram": 4.88232421875
        }
    ]
}