{
    "info": {
        "device": "cuda",
        "epoch": 10,
        "dataset": "stl10",
        "bs": 128,
        "data_path": "/host/ubuntu/torch",
        "arch": "dino_vitb16",
        "lr": 0.001,
        "stats_json": "./logs/stats/stats_210621_205415.json"
    },
    "telem": {
        "hardware": "1x3090",
        "gpu_total_memory": 23.69952392578125,
        "sample_count_train": 5000,
        "sample_count_val": 8000
    },
    "train": [
        {
            "epoch": 1,
            "time_start": 1624308871.7458904,
            "time_finish": 1624308878.2715127,
            "time_cost": 6.525622367858887,
            "loss": 1.3533051613718272,
            "acc": 0.5798,
            "vram": 6.04443359375
        },
        {
            "epoch": 2,
            "time_start": 1624308887.3074634,
            "time_finish": 1624308893.0957935,
            "time_cost": 5.788330078125,
            "loss": 0.08754463153891265,
            "acc": 0.975,
            "vram": 6.04443359375
        },
        {
            "epoch": 3,
            "time_start": 1624308902.1522295,
            "time_finish": 1624308908.0365891,
            "time_cost": 5.88435959815979,
            "loss": 0.016513152874540537,
            "acc": 0.9986,
            "vram": 6.04443359375
        },
        {
            "epoch": 4,
            "time_start": 1624308917.128408,
            "time_finish": 1624308922.9153984,
            "time_cost": 5.786990404129028,
            "loss": 0.005101536243455484,
            "acc": 0.9998,
            "vram": 6.04443359375
        },
        {
            "epoch": 5,
            "time_start": 1624308932.0508037,
            "time_finish": 1624308937.8950331,
            "time_cost": 5.844229459762573,
            "loss": 0.0028664763871347533,
            "acc": 1.0,
            "vram": 6.04443359375
        },
        {
            "epoch": 6,
            "time_start": 1624308947.0837412,
            "time_finish": 1624308952.9913142,
            "time_cost": 5.907572984695435,
            "loss": 0.0020201586827170103,
            "acc": 1.0,
            "vram": 6.04443359375
        },
        {
            "epoch": 7,
            "time_start": 1624308962.14165,
            "time_finish": 1624308968.0369654,
            "time_cost": 5.895315408706665,
            "loss": 0.0016166662593604998,
            "acc": 1.0,
            "vram": 6.04443359375
        },
        {
            "epoch": 8,
            "time_start": 1624308977.1107814,
            "time_finish": 1624308982.9459186,
            "time_cost": 5.835137128829956,
            "loss": 0.001292327488772571,
            "acc": 1.0,
            "vram": 6.04443359375
        },
        {
            "epoch": 9,
            "time_start": 1624308992.0894568,
            "time_finish": 1624308998.0231829,
            "time_cost": 5.933726072311401,
            "loss": 0.0010681487940018997,
            "acc": 1.0,
            "vram": 6.04443359375
        },
        {
            "epoch": 10,
            "time_start": 1624309007.2443416,
            "time_finish": 1624309013.1721532,
            "time_cost": 5.927811622619629,
            "loss": 0.000942336703883484,
            "acc": 1.0,
            "vram": 6.04443359375
        }
    ],
    "val": [
        {
            "epoch": 1,
            "time_start": 1624308878.2730653,
            "time_finish": 1624308887.3044407,
            "time_cost": 9.031375408172607,
            "loss": 0.16475252925403536,
            "acc": 0.956,
            "vram": 6.04443359375
        },
        {
            "epoch": 2,
            "time_start": 1624308893.0970254,
            "time_finish": 1624308902.1488838,
            "time_cost": 9.05185842514038,
            "loss": 0.03437314362871268,
            "acc": 0.992875,
            "vram": 6.04443359375
        },
        {
            "epoch": 3,
            "time_start": 1624308908.0377111,
            "time_finish": 1624308917.124315,
            "time_cost": 9.086603879928589,
            "loss": 0.007922610774311044,
            "acc": 0.999875,
            "vram": 6.04443359375
        },
        {
            "epoch": 4,
            "time_start": 1624308922.916785,
            "time_finish": 1624308932.0465567,
            "time_cost": 9.129771709442139,
            "loss": 0.0036591102539132985,
            "acc": 1.0,
            "vram": 6.04443359375
        },
        {
            "epoch": 5,
            "time_start": 1624308937.8959842,
            "time_finish": 1624308947.0794086,
            "time_cost": 9.183424472808838,
            "loss": 0.0024581029974219816,
            "acc": 1.0,
            "vram": 6.04443359375
        },
        {
            "epoch": 6,
            "time_start": 1624308952.992747,
            "time_finish": 1624308962.136817,
            "time_cost": 9.144069910049438,
            "loss": 0.001853559068256309,
            "acc": 1.0,
            "vram": 6.04443359375
        },
        {
            "epoch": 7,
            "time_start": 1624308968.0380547,
            "time_finish": 1624308977.107424,
            "time_cost": 9.069369316101074,
            "loss": 0.001484034300249602,
            "acc": 1.0,
            "vram": 6.04443359375
        },
        {
            "epoch": 8,
            "time_start": 1624308982.9471824,
            "time_finish": 1624308992.0858133,
            "time_cost": 9.138630867004395,
            "loss": 0.0012286746641620994,
            "acc": 1.0,
            "vram": 6.04443359375
        },
        {
            "epoch": 9,
            "time_start": 1624308998.0246382,
            "time_finish": 1624309007.2403955,
            "time_cost": 9.215757369995117,
            "loss": 0.0010464371686490874,
            "acc": 1.0,
            "vram": 6.04443359375
        },
        {
            "epoch": 10,
            "time_start": 1624309013.173618,
            "time_finish": 1624309022.366928,
            "time_cost": 9.193310022354126,
            "loss": 0.0009090362406808823,
            "acc": 1.0,
            "vram": 6.04443359375
        }
    ]
}